{"stats":{"minecraft:picked_up":{"minecraft:repeater":2,"minecraft:glow_item_frame":3,"minecraft:quartz_pillar":1,"minecraft:stone_button":1,"minecraft:trident":2,"minecraft:redstone":3,"minecraft:quartz_block":1,"minecraft:netherite_sword":1,"minecraft:comparator":1,"minecraft:armadillo_scute":3,"minecraft:redstone_torch":1,"minecraft:chest":1,"minecraft:nether_star":1,"minecraft:blaze_powder":224,"minecraft:hopper":2},"minecraft:dropped":{"minecraft:trident":2,"minecraft:hopper":3,"minecraft:netherite_sword":1,"minecraft:chest":1,"minecraft:redstone_torch":1,"minecraft:armadillo_scute":1,"minecraft:quartz_pillar":1},"minecraft:killed":{"minecraft:wither":1},"minecraft:custom":{"minecraft:time_since_rest":186258,"minecraft:sprint_one_cm":6919,"minecraft:inspect_dropper":22,"minecraft:walk_one_cm":174984,"minecraft:mob_kills":2,"minecraft:drop":10,"minecraft:inspect_hopper":18,"minecraft:damage_dealt":1844,"minecraft:fly_one_cm":283294,"minecraft:open_barrel":8,"minecraft:open_chest":16,"minecraft:crouch_one_cm":3252,"minecraft:play_time":224801,"minecraft:sneak_time":5210,"minecraft:jump":393,"minecraft:interact_with_brewingstand":3,"minecraft:leave_game":3,"minecraft:time_since_death":224801,"minecraft:sleep_in_bed":2,"minecraft:climb_one_cm":522,"minecraft:total_world_time":225763},"minecraft:used":{"minecraft:shroomlight":61,"minecraft:redstone_torch":58,"minecraft:sticky_piston":10,"minecraft:dark_oak_stairs":1,"minecraft:lever":2,"minecraft:netherite_sword":44,"minecraft:crying_obsidian":82,"minecraft:quartz_pillar":125,"minecraft:dropper":22,"minecraft:wither_skeleton_skull":3,"minecraft:quartz_slab":35,"minecraft:iron_block":35,"minecraft:grass_block":18,"minecraft:redstone":78,"minecraft:spruce_button":1,"minecraft:stone_button":10,"minecraft:quartz_block":131,"minecraft:chest":14,"minecraft:quartz_stairs":129,"minecraft:barrel":4,"minecraft:torch":4,"minecraft:glow_item_frame":22,"minecraft:orange_bed":1,"minecraft:chiseled_stone_bricks":72,"minecraft:repeater":13,"minecraft:brewing_stand":3,"minecraft:redstone_lamp":20,"minecraft:soul_sand":4,"minecraft:comparator":31,"minecraft:hopper":46,"minecraft:gold_block":138,"minecraft:waxed_copper_bulb":2}},"DataVersion":4189}